.travis.yml
AUTHORS
ChangeLog
LICENSE
README.rst
install.sh
setup.cfg
setup.py
upload_pypi.sh
PyConfDict.egg-info/PKG-INFO
PyConfDict.egg-info/SOURCES.txt
PyConfDict.egg-info/dependency_links.txt
PyConfDict.egg-info/not-zip-safe
PyConfDict.egg-info/pbr.json
PyConfDict.egg-info/top_level.txt
examples/dict1.json
examples/dict2.json
examples/examples.py
pyconfdict/__init__.py