Metadata-Version: 1.1
Name: PyConfDict
Version: 0.0.1.dev3
Summary: Python configuration dictionary
Home-page: http://github.com/karel-brinda/rnftools/
Author: Karel Brinda
Author-email: karel.brinda@gmail.com
License: MIT
Keywords: configuration,dictionary
Platform: UNKNOWN
Classifier: Development Status :: 4 - Beta
Classifier: Environment :: Console
Classifier: License :: OSI Approved :: MIT License
Classifier: Natural Language :: English
Classifier: Programming Language :: Python :: 3
